sem_meter_client/__init__.py
sem_meter_client/circuit.py
sem_meter_client/equipment.py
sem_meter_client/sem_meter_client.py
sem_meter_client/user.py
tests/__init__.py
tests/test__init__.py
tests/test_circuit.py
tests/test_equipment.py
tests/test_live.py
tests/test_sem_meter_client.py
tests/test_user.py
sem_meter_client-0.0.1.dist-info/LICENSE
sem_meter_client-0.0.1.dist-info/METADATA
sem_meter_client-0.0.1.dist-info/WHEEL
sem_meter_client-0.0.1.dist-info/top_level.txt
sem_meter_client-0.0.1.dist-info/RECORD
